gtrending/__init__.py
gtrending/__main__.py
gtrending/_data/__init__.py
gtrending/_data/languages.json
gtrending/_data/spoken_languages.json
gtrending/cli.py
gtrending/fetch.py
gtrending/paramutils.py
gtrending/scrape.py
gtrending-0.5.1.dist-info/LICENSE
gtrending-0.5.1.dist-info/METADATA
gtrending-0.5.1.dist-info/WHEEL
gtrending-0.5.1.dist-info/entry_points.txt
gtrending-0.5.1.dist-info/RECORD
