Metadata-Version: 2.1
Name: gtrending
Version: 0.5.1
Summary: Trending repositories and developers on GitHu
Home-page: https://github.com/hedyhli/gtrending
License: MIT
Keywords: github,github-trending
Author: hedy
Author-email: hedy@tilde.cafe
Requires-Python: >=3.8,<4.0
Classifier: Environment :: Console
Classifier: Intended Audience :: Developers
Classifier: License :: OSI Approved :: MIT License
Classifier: Operating System :: MacOS
Classifier: Operating System :: Microsoft :: Windows
Classifier: Operating System :: POSIX :: Linux
Classifier: Programming Language :: Python :: 3
Classifier: Programming Language :: Python :: 3.8
Classifier: Programming Language :: Python :: 3.9
Classifier: Programming Language :: Python :: 3.10
Classifier: Programming Language :: Python :: 3.11
Classifier: Topic :: Software Development :: Libraries :: Python Modules
Classifier: Typing :: Typed
Requires-Dist: beautifulsoup4 (>=4.12.2,<5.0.0)
Requires-Dist: requests (>=2.31.0,<3.0.0)
Project-URL: Documentation, https://gtrending.readthedocs.io/en/latest/
Project-URL: Repository, https://github.com/hedyhli/gtrending
